{"error": false, "size": [1920, 1080], "name": "\u041f\u0440\u043e\u0449\u0430\u0432\u0430\u0439, \u041e\u0430\u0437\u043e", "version": "", "location": {"label": {"splashscreen": ["game/code/init/gui.rpy", 91], "start": ["game/code/init/script.rpy", 3], "scene_ten": ["game/code/scene (10)/scene10.rpy", 1], "proval_10": ["game/code/scene (10)/scene10.rpy", 230], "scene_eleven": ["game/code/scene (11)/scene11.rpy", 1], "scene_twelve": ["game/code/scene (12)/scene12.rpy", 1], "scene_thirteen": ["game/code/scene (13)/scene13.rpy", 1], "scene_final": ["game/code/scene (14)/scene14.rpy", 1], "scene_two": ["game/code/scene (2)/scene2.rpy", 1], "scene_three": ["game/code/scene (3)/scene 3.rpy", 1], "scene_four": ["game/code/scene (4)/scene4.rpy", 1], "scene_five": ["game/code/scene (5)/scene5.rpy", 1], "scene_six": ["game/code/scene (6)/scene6.rpy", 2], "scene_seven": ["game/code/scene (7)/scene7.rpy", 2], "scene_eight": ["game/code/scene (8)/scene 8.rpy", 2], "street": ["game/code/scene (8)/scene 8.rpy", 141], "proval": ["game/code/scene (8)/scene 8.rpy", 286], "proval2": ["game/code/scene (8)/scene 8.rpy", 296], "proval3": ["game/code/scene (8)/scene 8.rpy", 314], "brama": ["game/code/scene (8)/scene 8.rpy", 325], "proval_brama": ["game/code/scene (8)/scene 8.rpy", 516], "scene_eight_end": ["game/code/scene (8)/scene 8.rpy", 526], "scene_nine": ["game/code/scene (9)/scene 9.rpy", 2]}, "define": {"gui.accent_color": ["game/code/init/gui.rpy", 26], "gui.idle_color": ["game/code/init/gui.rpy", 30], "gui.idle_small_color": ["game/code/init/gui.rpy", 34], "gui.hover_color": ["game/code/init/gui.rpy", 37], "gui.selected_color": ["game/code/init/gui.rpy", 41], "gui.insensitive_color": ["game/code/init/gui.rpy", 44], "gui.muted_color": ["game/code/init/gui.rpy", 49], "gui.hover_muted_color": ["game/code/init/gui.rpy", 50], "gui.text_color": ["game/code/init/gui.rpy", 53], "gui.interface_text_color": ["game/code/init/gui.rpy", 54], "gui.text_font": ["game/code/init/gui.rpy", 60], "gui.name_text_font": ["game/code/init/gui.rpy", 63], "gui.interface_text_outlines": ["game/code/init/gui.rpy", 65], "gui.interface_text_font": ["game/code/init/gui.rpy", 68], "gui.text_size": ["game/code/init/gui.rpy", 71], "gui.name_text_size": ["game/code/init/gui.rpy", 74], "gui.interface_text_size": ["game/code/init/gui.rpy", 77], "gui.label_text_size": ["game/code/init/gui.rpy", 80], "gui.notify_text_size": ["game/code/init/gui.rpy", 83], "gui.title_text_size": ["game/code/init/gui.rpy", 86], "gui.main_menu_background": ["game/code/init/gui.rpy", 123], "gui.game_menu_background": ["game/code/init/gui.rpy", 124], "gui.textbox_height": ["game/code/init/gui.rpy", 133], "gui.textbox_yalign": ["game/code/init/gui.rpy", 137], "gui.name_xpos": ["game/code/init/gui.rpy", 142], "gui.name_ypos": ["game/code/init/gui.rpy", 143], "gui.name_xalign": ["game/code/init/gui.rpy", 148], "gui.namebox_width": ["game/code/init/gui.rpy", 152], "gui.namebox_height": ["game/code/init/gui.rpy", 153], "gui.namebox_borders": ["game/code/init/gui.rpy", 156], "gui.namebox_tile": ["game/code/init/gui.rpy", 160], "gui.dialogue_xpos": ["game/code/init/gui.rpy", 165], "gui.dialogue_ypos": ["game/code/init/gui.rpy", 166], "gui.dialogue_width": ["game/code/init/gui.rpy", 169], "gui.dialogue_text_xalign": ["game/code/init/gui.rpy", 174], "gui.button_width": ["game/code/init/gui.rpy", 183], "gui.button_height": ["game/code/init/gui.rpy", 184], "gui.button_borders": ["game/code/init/gui.rpy", 187], "gui.button_tile": ["game/code/init/gui.rpy", 191], "gui.button_text_font": ["game/code/init/gui.rpy", 194], "gui.button_text_size": ["game/code/init/gui.rpy", 197], "gui.button_text_idle_color": ["game/code/init/gui.rpy", 200], "gui.button_text_hover_color": ["game/code/init/gui.rpy", 201], "gui.button_text_selected_color": ["game/code/init/gui.rpy", 202], "gui.button_text_insensitive_color": ["game/code/init/gui.rpy", 203], "gui.button_text_xalign": ["game/code/init/gui.rpy", 207], "gui.radio_button_borders": ["game/code/init/gui.rpy", 216], "gui.check_button_borders": ["game/code/init/gui.rpy", 218], "gui.confirm_button_text_xalign": ["game/code/init/gui.rpy", 220], "gui.page_button_borders": ["game/code/init/gui.rpy", 222], "gui.quick_button_borders": ["game/code/init/gui.rpy", 224], "gui.quick_button_text_size": ["game/code/init/gui.rpy", 225], "gui.quick_button_text_idle_color": ["game/code/init/gui.rpy", 226], "gui.quick_button_text_selected_color": ["game/code/init/gui.rpy", 227], "gui.choice_button_width": ["game/code/init/gui.rpy", 240], "gui.choice_button_height": ["game/code/init/gui.rpy", 241], "gui.choice_button_tile": ["game/code/init/gui.rpy", 242], "gui.choice_button_borders": ["game/code/init/gui.rpy", 243], "gui.choice_button_text_font": ["game/code/init/gui.rpy", 244], "gui.choice_button_text_size": ["game/code/init/gui.rpy", 245], "gui.choice_button_text_xalign": ["game/code/init/gui.rpy", 246], "gui.choice_button_text_idle_color": ["game/code/init/gui.rpy", 247], "gui.choice_button_text_hover_color": ["game/code/init/gui.rpy", 248], "gui.choice_button_text_insensitive_color": ["game/code/init/gui.rpy", 249], "gui.slot_button_width": ["game/code/init/gui.rpy", 259], "gui.slot_button_height": ["game/code/init/gui.rpy", 260], "gui.slot_button_borders": ["game/code/init/gui.rpy", 261], "gui.slot_button_text_size": ["game/code/init/gui.rpy", 262], "gui.slot_button_text_xalign": ["game/code/init/gui.rpy", 263], "gui.slot_button_text_idle_color": ["game/code/init/gui.rpy", 264], "gui.slot_button_text_selected_idle_color": ["game/code/init/gui.rpy", 265], "gui.slot_button_text_selected_hover_color": ["game/code/init/gui.rpy", 266], "config.thumbnail_width": ["game/code/init/gui.rpy", 270], "config.thumbnail_height": ["game/code/init/gui.rpy", 271], "gui.file_slot_cols": ["game/code/init/gui.rpy", 274], "gui.file_slot_rows": ["game/code/init/gui.rpy", 275], "gui.navigation_xpos": ["game/code/init/gui.rpy", 284], "gui.skip_ypos": ["game/code/init/gui.rpy", 287], "gui.notify_ypos": ["game/code/init/gui.rpy", 290], "gui.choice_spacing": ["game/code/init/gui.rpy", 293], "gui.navigation_spacing": ["game/code/init/gui.rpy", 296], "gui.pref_spacing": ["game/code/init/gui.rpy", 299], "gui.pref_button_spacing": ["game/code/init/gui.rpy", 302], "gui.page_spacing": ["game/code/init/gui.rpy", 305], "gui.slot_spacing": ["game/code/init/gui.rpy", 308], "gui.main_menu_text_xalign": ["game/code/init/gui.rpy", 311], "gui.frame_borders": ["game/code/init/gui.rpy", 320], "gui.confirm_frame_borders": ["game/code/init/gui.rpy", 323], "gui.skip_frame_borders": ["game/code/init/gui.rpy", 326], "gui.notify_frame_borders": ["game/code/init/gui.rpy", 329], "gui.frame_tile": ["game/code/init/gui.rpy", 332], "gui.bar_size": ["game/code/init/gui.rpy", 345], "gui.scrollbar_size": ["game/code/init/gui.rpy", 346], "gui.slider_size": ["game/code/init/gui.rpy", 347], "gui.bar_tile": ["game/code/init/gui.rpy", 351], "gui.scrollbar_tile": ["game/code/init/gui.rpy", 352], "gui.slider_tile": ["game/code/init/gui.rpy", 353], "gui.bar_borders": ["game/code/init/gui.rpy", 356], "gui.scrollbar_borders": ["game/code/init/gui.rpy", 357], "gui.slider_borders": ["game/code/init/gui.rpy", 358], "gui.vbar_borders": ["game/code/init/gui.rpy", 361], "gui.vscrollbar_borders": ["game/code/init/gui.rpy", 362], "gui.vslider_borders": ["game/code/init/gui.rpy", 363], "gui.unscrollable": ["game/code/init/gui.rpy", 367], "config.history_length": ["game/code/init/gui.rpy", 375], "gui.history_height": ["game/code/init/gui.rpy", 379], "gui.history_name_xpos": ["game/code/init/gui.rpy", 383], "gui.history_name_ypos": ["game/code/init/gui.rpy", 384], "gui.history_name_width": ["game/code/init/gui.rpy", 385], "gui.history_name_xalign": ["game/code/init/gui.rpy", 386], "gui.history_text_xpos": ["game/code/init/gui.rpy", 389], "gui.history_text_ypos": ["game/code/init/gui.rpy", 390], "gui.history_text_width": ["game/code/init/gui.rpy", 391], "gui.history_text_xalign": ["game/code/init/gui.rpy", 392], "gui.nvl_borders": ["game/code/init/gui.rpy", 401], "gui.nvl_list_length": ["game/code/init/gui.rpy", 405], "gui.nvl_height": ["game/code/init/gui.rpy", 409], "gui.nvl_spacing": ["game/code/init/gui.rpy", 413], "gui.nvl_name_xpos": ["game/code/init/gui.rpy", 417], "gui.nvl_name_ypos": ["game/code/init/gui.rpy", 418], "gui.nvl_name_width": ["game/code/init/gui.rpy", 419], "gui.nvl_name_xalign": ["game/code/init/gui.rpy", 420], "gui.nvl_text_xpos": ["game/code/init/gui.rpy", 423], "gui.nvl_text_ypos": ["game/code/init/gui.rpy", 424], "gui.nvl_text_width": ["game/code/init/gui.rpy", 425], "gui.nvl_text_xalign": ["game/code/init/gui.rpy", 426], "gui.nvl_thought_xpos": ["game/code/init/gui.rpy", 430], "gui.nvl_thought_ypos": ["game/code/init/gui.rpy", 431], "gui.nvl_thought_width": ["game/code/init/gui.rpy", 432], "gui.nvl_thought_xalign": ["game/code/init/gui.rpy", 433], "gui.nvl_button_xpos": ["game/code/init/gui.rpy", 436], "gui.nvl_button_xalign": ["game/code/init/gui.rpy", 437], "gui.language": ["game/code/init/gui.rpy", 445], "quick_menu": ["game/code/init/screens.rpy", 278], "gui.history_allow_tags": ["game/code/init/screens.rpy", 947], "config.nvl_list_length": ["game/code/init/screens.rpy", 1375], "\u043d\u0435\u0432\u0456\u0434\u043e\u043c\u0438\u0439": ["game/code/init/init.rpy", 1], "\u043f\u0430\u0432\u043a\u0430": ["game/code/init/init.rpy", 3], "\u0456\u043d\u043a\u0456": ["game/code/init/init.rpy", 5], "\u043b\u0430\u0439\u044f": ["game/code/scene (3)/scene 3.rpy", 612], "\u0440\u043e\u0431\u0456": ["game/code/scene (5)/scene5.rpy", 165], "\u0434\u0435\u043c\u043e\u043d": ["game/code/init/init.rpy", 11], "\u043a\u0456\u043c\u043d\u0430\u0442\u0430": ["game/code/init/init.rpy", 13], "\u0433\u0443\u0447\u043d\u043e\u043c\u043e\u0432\u0435\u0446\u044c": ["game/code/init/init.rpy", 15], "\u0439\u0435\u0440\u0431\u0456": ["game/code/init/init.rpy", 17], "\u0433\u0435\u043d\u0442\u043e": ["game/code/init/init.rpy", 19], "\u0431\u0430\u0442\u044c\u043a\u043e": ["game/code/init/init.rpy", 21], "\u043c\u0430\u043c\u0430": ["game/code/init/init.rpy", 23], "\u0441\u0443\u0439\u0440\u0430": ["game/code/init/init.rpy", 25], "\u0430\u0432\u0442\u043e\u0432\u0456\u0434\u043f\u043e\u0432\u0456\u0434\u0430\u0447": ["game/code/init/init.rpy", 28], "\u043f\u0430\u0441\u0430\u0436\u0438\u0440\u043a\u0430": ["game/code/init/init.rpy", 30], "\u043f\u0435\u0440\u0435\u0432\u0456\u0440\u044f\u044e\u0447\u0438\u0439": ["game/code/init/init.rpy", 32], "\u0433\u043e\u043b\u043e\u0441": ["game/code/init/init.rpy", 35], "\u0433\u043e\u043b\u043e\u04411": ["game/code/init/init.rpy", 36], "\u0433\u043e\u043b\u043e\u04412": ["game/code/init/init.rpy", 37], "\u0445\u043b\u043e\u043f\u0435\u0446\u044c1": ["game/code/init/init.rpy", 38], "\u0445\u043b\u043e\u043f\u0435\u0446\u044c2": ["game/code/init/init.rpy", 39], "\u0432\u0456\u0434\u043d\u043e\u0441\u0438\u043d\u0438_\u043b\u0430\u0439\u044f": ["game/code/init/init.rpy", 53], "\u0432\u0456\u0434\u043d\u043e\u0441\u0438\u043d\u0438_\u0456\u043d\u043a\u0456": ["game/code/init/init.rpy", 54], "\u043d\u0435\u043f\u043e\u043c\u0456\u0442\u043d\u0456\u0441\u0442\u044c": ["game/code/init/init.rpy", 56], "\u0448\u0432\u0438\u0434\u043a\u0456\u0441\u0442\u044c": ["game/code/init/init.rpy", 57], "\u043f\u043e\u043a\u043e\u0440\u0430_\u043b\u0430\u0439\u0456": ["game/code/init/init.rpy", 59], "\u0433\u043e\u0434\u0456\u0443\u043c_\u0456\u043d\u043a\u0456": ["game/code/init/init.rpy", 61], "\u043b\u0430\u0439\u043a\u0430_\u0456\u043d\u043a\u0456": ["game/code/init/init.rpy", 62], "\u0448\u043e\u043a_\u0456\u043d\u043a\u0456": ["game/code/init/init.rpy", 63], "\u043e\u0431\u0456\u0446\u044f\u043d\u043a\u0430_\u0456\u043d\u043a\u0456": ["game/code/init/init.rpy", 64], "\u0432\u0442\u0435\u0447\u0430_\u0433\u043e\u0434\u0456\u0443\u043c": ["game/code/init/init.rpy", 66], "\u0432\u0443\u043b\u0438\u0446\u044f": ["game/code/init/init.rpy", 68], "\u0431\u0440\u0430\u043c\u0430": ["game/code/init/init.rpy", 69], "config.name": ["game/options.rpy", 16], "gui.show_name": ["game/options.rpy", 22], "config.version": ["game/options.rpy", 27], "gui.about": ["game/options.rpy", 32], "build.name": ["game/options.rpy", 42], "config.has_sound": ["game/options.rpy", 51], "config.has_music": ["game/options.rpy", 52], "config.has_voice": ["game/options.rpy", 53], "config.main_menu_music": ["game/options.rpy", 61], "config.enter_transition": ["game/options.rpy", 83], "config.exit_transition": ["game/options.rpy", 84], "config.intra_transition": ["game/options.rpy", 89], "config.after_load_transition": ["game/options.rpy", 94], "config.end_game_transition": ["game/options.rpy", 99], "config.window": ["game/options.rpy", 117], "config.window_show_transition": ["game/options.rpy", 122], "config.window_hide_transition": ["game/options.rpy", 123], "config.save_directory": ["game/options.rpy", 155], "config.window_icon": ["game/options.rpy", 162]}, "screen": {"say": ["game/code/init/screens.rpy", 99], "input": ["game/code/init/screens.rpy", 176], "countdown": ["game/code/init/screens.rpy", 215], "choice": ["game/code/init/screens.rpy", 219], "quick_menu": ["game/code/init/screens.rpy", 1444], "navigation": ["game/code/init/screens.rpy", 299], "main_menu": ["game/code/init/screens.rpy", 385], "game_menu": ["game/code/init/screens.rpy", 450], "about": ["game/code/init/screens.rpy", 577], "save": ["game/code/init/screens.rpy", 617], "load": ["game/code/init/screens.rpy", 624], "file_slots": ["game/code/init/screens.rpy", 631], "preferences": ["game/code/init/screens.rpy", 745], "history": ["game/code/init/screens.rpy", 906], "help": ["game/code/init/screens.rpy", 995], "keyboard_help": ["game/code/init/screens.rpy", 1024], "mouse_help": ["game/code/init/screens.rpy", 1075], "gamepad_help": ["game/code/init/screens.rpy", 1098], "confirm": ["game/code/init/screens.rpy", 1164], "skip_indicator": ["game/code/init/screens.rpy", 1227], "notify": ["game/code/init/screens.rpy", 1283], "nvl": ["game/code/init/screens.rpy", 1322], "nvl_dialogue": ["game/code/init/screens.rpy", 1354]}, "transform": {"alpha_dissolve": ["game/code/init/screens.rpy", 209], "delayed_blink": ["game/code/init/screens.rpy", 1245], "notify_appear": ["game/code/init/screens.rpy", 1294], "shaking": ["game/code/init/init.rpy", 41]}, "callable": {"touch": ["game/code/init/gui.rpy", 456], "small": ["game/code/init/gui.rpy", 463]}}, "build": {"directory_name": "Goodbye_Oaza", "executable_name": "Goodbye_Oaza", "include_update": false, "packages": [{"name": "pc", "formats": ["zip"], "file_lists": ["windows", "linux", "renpy", "all"], "description": "PC: Windows and Linux", "update": true, "dlc": false, "hidden": false}, {"name": "linux", "formats": ["tar.bz2"], "file_lists": ["linux", "linux_arm", "renpy", "all"], "description": "Linux", "update": true, "dlc": false, "hidden": false}, {"name": "mac", "formats": ["app-zip", "app-dmg"], "file_lists": ["mac", "renpy", "all"], "description": "Macintosh", "update": true, "dlc": false, "hidden": false}, {"name": "win", "formats": ["zip"], "file_lists": ["windows", "renpy", "all"], "description": "Windows", "update": true, "dlc": false, "hidden": false}, {"name": "market", "formats": ["bare-zip"], "file_lists": ["windows", "linux", "mac", "renpy", "all"], "description": "Windows, Mac, Linux for Markets", "update": true, "dlc": false, "hidden": false}, {"name": "steam", "formats": ["zip"], "file_lists": ["windows", "linux", "mac", "renpy", "all"], "description": "steam", "update": true, "dlc": false, "hidden": true}, {"name": "android", "formats": ["directory"], "file_lists": ["android", "all"], "description": "android", "update": false, "dlc": true, "hidden": true}, {"name": "ios", "formats": ["directory"], "file_lists": ["ios", "all"], "description": "ios", "update": false, "dlc": true, "hidden": true}, {"name": "web", "formats": ["zip"], "file_lists": ["web", "all"], "description": "web", "update": false, "dlc": true, "hidden": true}], "archives": [["archive", ["all"]]], "documentation_patterns": ["*.html", "*.txt"], "base_patterns": [["*.py", null], ["*.sh", null], ["*.app/", null], ["*.dll", null], ["*.manifest", null], ["lib/", null], ["renpy/", null], ["update/", null], ["common/", null], ["update/", null], ["old-game/", null], ["icon.ico", null], ["icon.icns", null], ["project.json", null], ["log.txt", null], ["errors.txt", null], ["traceback.txt", null], ["image_cache.txt", null], ["text_overflow.txt", null], ["dialogue.txt", null], ["dialogue.tab", null], ["profile_screen.txt", null], ["files.txt", null], ["memory.txt", null], ["tmp/", null], ["game/saves/", null], ["game/bytecode.rpyb", null], ["archived/", null], ["launcherinfo.py", null], ["android.txt", null], ["game/presplash*.*", ["all"]], [".android.json", ["android"]], ["android-*.png", ["android"]], ["android-*.jpg", ["android"]], ["ouya_icon.png", null], ["ios-presplash.*", ["ios"]], ["ios-launchimage.png", null], ["ios-icon.png", null], ["web-presplash.png", ["web"]], ["web-presplash.jpg", ["web"]], ["web-presplash.webp", ["web"]], ["progressive_download.txt", ["web"]], ["steam_appid.txt", null], ["**~", null], ["**.bak", null], ["**/.**", null], ["**/#**", null], ["**/thumbs.db", null], [".*", null], ["**", ["all"]]], "renpy_patterns": [["renpy/common/_compat/**", null], ["renpy/common/_roundrect/**", null], ["renpy/common/_outline/**", null], ["renpy/common/_theme**", null], ["lib/**/_ssl.*", null], ["renpy/**__pycache__/**.cpython-39.pyc", ["all"]], ["renpy/**__pycache__", ["all"]], ["**~", null], ["**/#*", null], ["**/.*", null], ["**.old", null], ["**.new", null], ["**.rpa", null], ["**/steam_appid.txt", null], ["renpy.py", ["all"]], ["renpy/", ["all"]], ["renpy/**.py", ["renpy"]], ["renpy/**.pxd", null], ["renpy/**.pxi", null], ["renpy/**.pyx", null], ["renpy/**.pyc", null], ["renpy/**.pyo", null], ["renpy/common/", ["all"]], ["renpy/common/_compat/**", ["renpy"]], ["renpy/common/**.rpy", ["renpy"]], ["renpy/common/**.rpym", ["renpy"]], ["renpy/common/_compat/**", ["renpy"]], ["renpy/common/**", ["all"]], ["renpy/**", ["all"]], ["lib/*/renpy", null], ["lib/*/renpy.exe", null], ["lib/*/pythonw.exe", null], ["lib/py2-*/", null], ["lib/py*-windows-i686/**", ["windows_i686"]], ["lib/py*-windows-x86_64/**", ["windows"]], ["lib/py*-linux-i686/**", ["linux_i686"]], ["lib/py*-linux-aarch64/**", ["linux_arm"]], ["lib/py*-linux-armv7l/**", ["linux_arm"]], ["lib/py*-linux-*/**", ["linux"]], ["lib/py*-mac-*/**", ["mac"]], ["lib/python2.*/**", null], ["lib/**", ["windows", "linux", "mac", "android", "ios"]], ["renpy.sh", ["linux", "mac"]]], "xbit_patterns": ["**.sh", "lib/py*-linux-*/*", "lib/py*-mac-*/*", "**.app/Contents/MacOS/*"], "version": "Goodbye_Oaza", "display_name": "\u041f\u0440\u043e\u0449\u0430\u0432\u0430\u0439, \u041e\u0430\u0437\u043e", "exclude_empty_directories": true, "allow_integrated_gpu": true, "renpy": false, "script_version": true, "destination": "Goodbye_Oaza-dists", "mac_info_plist": {}, "merge": [["linux_i686", "linux"], ["windows_i686", "windows"]], "include_i686": true, "change_icon_i686": true, "android_permissions": [], "_sdk_fonts": false}}